tieval/__init__.py
tieval/__main__.py
tieval/base.py
tieval/closure.py
tieval/entities.py
tieval/links.py
tieval/temporal_relation.py
tieval/utils.py
tieval/datasets/__init__.py
tieval/datasets/metadata.py
tieval/datasets/utils.py
tieval/datasets/readers/__init__.py
tieval/datasets/readers/dataset.py
tieval/datasets/readers/document.py
tieval/evaluate/__init__.py
tieval/evaluate/metrics.py
tieval/models/__init__.py
tieval/models/base.py
tieval/models/metadata.py
tieval/models/identification/__init__.py
tieval/models/identification/event.py
tieval/models/identification/timex.py
tieval-0.1.11.dist-info/licenses/LICENSE
tieval-0.1.11.dist-info/METADATA
tieval-0.1.11.dist-info/WHEEL
tieval-0.1.11.dist-info/top_level.txt
tieval-0.1.11.dist-info/RECORD
