Metadata-Version: 2.4
Name: tieval
Version: 0.1.11
Summary: A framework for evaluation and development of temporal-aware models.
Author-email: Hugo Sousa <hugo.o.sousa@inesctec.pt>
Maintainer-email: Hugo Sousa <hugo.o.sousa@inesctec.pt>
License: MIT License
Project-URL: Documentation, https://tieval.readthedocs.io/
Project-URL: Repository, https://github.com/LIAAD/tieval
Keywords: temporal information,evaluation,temporal information extraction,temporal relation classification,temporal relation extraction,temporal expression identification,event identification,event classification
Classifier: Development Status :: 2 - Pre-Alpha
Classifier: License :: OSI Approved :: MIT License
Classifier: Programming Language :: Python
Classifier: Programming Language :: Python :: 3.8
Classifier: Programming Language :: Python :: 3.9
Classifier: Programming Language :: Python :: 3.10
Requires-Python: >=3.8
License-File: LICENSE
Requires-Dist: nltk
Requires-Dist: xmltodict
Requires-Dist: networkx>=2.8.1
Requires-Dist: cached-path>=1.1.2
Provides-Extra: test
Requires-Dist: pytest; extra == "test"
Provides-Extra: models
Requires-Dist: allennlp==2.9.3; extra == "models"
Requires-Dist: py_heideltime; extra == "models"
Dynamic: license-file
